seashells/__init__.py
seashells/cli.py
seashells-1.0.0.dist-info/METADATA
seashells-1.0.0.dist-info/WHEEL
seashells-1.0.0.dist-info/entry_points.txt
seashells-1.0.0.dist-info/licenses/LICENSE.md
seashells-1.0.0.dist-info/RECORD
