Metadata-Version: 2.4
Name: seashells
Version: 1.0.0
Summary: The official client for Seashells.io
Project-URL: homepage, https://github.com/anishathalye/seashells
Project-URL: repository, https://github.com/anishathalye/seashells.git
Project-URL: issues, https://github.com/anishathalye/seashells/issues
Author-email: Anish Athalye <me@anishathalye.com>
License-File: LICENSE.md
Keywords: seashells,seashells.io,shell
Classifier: Development Status :: 5 - Production/Stable
Classifier: Intended Audience :: Developers
Classifier: License :: OSI Approved :: MIT License
Classifier: Programming Language :: Python :: 2
Classifier: Programming Language :: Python :: 3
Classifier: Topic :: Software Development :: Version Control
Classifier: Topic :: Utilities
Requires-Python: >=2.7
